License.md
MANIFEST.in
PatentNotice.md
README.md
setup.py
dqc_us_rules/__init__.py
dqc_us_rules/_pkg_meta.py
dqc_us_rules/dqc_us_0001.py
dqc_us_rules/dqc_us_0004.py
dqc_us_rules/dqc_us_0005.py
dqc_us_rules/dqc_us_0006.py
dqc_us_rules/dqc_us_0009.py
dqc_us_rules/dqc_us_0013.py
dqc_us_rules/dqc_us_0014.py
dqc_us_rules/dqc_us_0015.py
dqc_us_rules/dqc_us_0018.py
dqc_us_rules/dqc_us_0033_0036.py
dqc_us_rules/dqc_us_0041.py
dqc_us_rules.egg-info/PKG-INFO
dqc_us_rules.egg-info/SOURCES.txt
dqc_us_rules.egg-info/dependency_links.txt
dqc_us_rules.egg-info/top_level.txt
dqc_us_rules.egg-info/zip-safe
dqc_us_rules/resources/.DS_Store
dqc_us_rules/resources/DQC_US_0001/.DS_Store
dqc_us_rules/resources/DQC_US_0001/dqc_0001.json
dqc_us_rules/resources/DQC_US_0001/dqc_0001_2014.json
dqc_us_rules/resources/DQC_US_0001/dqc_0001_2015.json
dqc_us_rules/resources/DQC_US_0001/dqc_0001_2016.json
dqc_us_rules/resources/DQC_US_0001/dqc_0001_2017.json
dqc_us_rules/resources/DQC_US_0006/dqc_06_date_bounds.csv
dqc_us_rules/resources/DQC_US_0009/dqc_us_9_config.csv
dqc_us_rules/resources/DQC_US_0013/dqc_13_concepts.csv
dqc_us_rules/resources/DQC_US_0014/dqc_14_concepts.csv
dqc_us_rules/resources/DQC_US_0015/dqc_15_concepts.csv
dqc_us_rules/resources/DQC_US_0015/dqc_15_exclusion_rules.csv
dqc_us_rules/resources/DQC_US_0018/2014_deprecated-concepts.json
dqc_us_rules/resources/DQC_US_0018/2015_deprecated-concepts.json
dqc_us_rules/resources/DQC_US_0018/2016_deprecated-concepts.json
dqc_us_rules/resources/DQC_US_0018/2017_deprecated-concepts.json
dqc_us_rules/resources/DQC_US_0041/2014_ugt-default-dimensions.json
dqc_us_rules/resources/DQC_US_0041/2015_ugt-default-dimensions.json
dqc_us_rules/resources/DQC_US_0041/2016_ugt-default-dimensions.json
dqc_us_rules/resources/DQC_US_0041/2017_ugt-default-dimensions.json
dqc_us_rules/util/__init__.py
dqc_us_rules/util/facts.py
dqc_us_rules/util/message_info.json
dqc_us_rules/util/messages.py
dqc_us_rules/util/neg_num.py
dqc_us_rules/util/__pycache__/__init__.cpython-34.pyc
dqc_us_rules/util/__pycache__/facts.cpython-34.pyc
dqc_us_rules/util/__pycache__/messages.cpython-34.pyc
dqc_us_rules/util/__pycache__/neg_num.cpython-34.pyc