Metadata-Version: 1.1
Name: dqc-us-rules
Version: 3.5.0
Summary: UNKNOWN
Home-page: https://github.com/DataQualityCommittee/dqc_us_rules
Author: Data Quality Committee
Author-email: dqc@xbrl.us
License: UNKNOWN
Platform: UNKNOWN
Classifier: Development Status :: 5 - Production/Stable
Classifier: Intended Audience :: Developers
Classifier: License :: Other/Proprietary License
Classifier: Natural Language :: English
Classifier: Programming Language :: Python :: 3.4
Classifier: Topic :: Office/Business :: Financial :: Accounting
